drb_impl_http/__init__.py
drb_impl_http/_version.py
drb_impl_http/cortex.yml
drb_impl_http/drb_impl_http.py
drb_impl_http/execptions.py
drb_impl_http/oauth2/HTTPOAuth2.py
drb_impl_http/oauth2/__init__.py
drb_impl_http/oauth2/oauth2.py
drb_impl_http-1.0.9.data/data/requirements.txt
drb_impl_http-1.0.9.dist-info/METADATA
drb_impl_http-1.0.9.dist-info/WHEEL
drb_impl_http-1.0.9.dist-info/entry_points.txt
drb_impl_http-1.0.9.dist-info/top_level.txt
drb_impl_http-1.0.9.dist-info/RECORD
