Metadata-Version: 2.1
Name: drb-impl-http
Version: 1.0.9
Summary: DRB Http implementation
Home-page: https://gitlab.com/drb-python/impl/http
Author: GAEL Systems
Author-email: drb-python@gael.fr
License: UNKNOWN
Project-URL: Documentation, http://drb-python.gitlab.io/impl/http
Project-URL: Source, https://gitlab.com/drb-python/impl/http
Platform: UNKNOWN
Classifier: Programming Language :: Python :: 3.8
Classifier: License :: OSI Approved :: Apache Software License
Classifier: Operating System :: OS Independent
Requires-Python: >=3.8
Requires-Dist: drb (<1.1.0,>=1.0.4)
Requires-Dist: tenacity (==8.0.1)
